{
  "metadata": {
    "last_updated": "2026-04-09 09:29:57",
    "time_filter": "week",
    "subreddit": "opensource",
    "total_items": 20,
    "total_comments": 89,
    "file_size_bytes": 94673
  },
  "items": [
    {
      "id": "1sfdl6b",
      "title": "Microsoft terminates account of VeraCrypt developer",
      "subreddit": "opensource",
      "url": "https://sourceforge.net/p/veracrypt/discussion/general/thread/9620d7a4b3/",
      "author": "Fear_The_Creeper",
      "created_utc": "2026-04-08 00:23:11",
      "score": 466,
      "num_comments": 50,
      "upvote_ratio": 0.98,
      "text": "[External Link]",
      "is_original_content": false,
      "link_flair_text": "Discussion",
      "permalink": "https://reddit.com/r/opensource/comments/1sfdl6b/microsoft_terminates_account_of_veracrypt/",
      "domain": "sourceforge.net",
      "is_self": false,
      "comments": [
        {
          "id": "oex5h1r",
          "author": "TEK1_AU",
          "text": "What’s the TL;DR / reason for this?",
          "score": 62,
          "created_utc": "2026-04-08 02:09:08",
          "is_submitter": false,
          "replies": [
            {
              "id": "oexaflg",
              "author": "Fear_The_Creeper",
              "text": "I have two equally reasonable theories, and one conspiracy theory.\n\nReasonable theory #1: Giant corporation screws up, and it is impossible to get them to notice until there is a story in the New York Times.\n\nReasonable theory #2: Microsoft simply does not trust anyone that doesn't have an employee badge to run code before Windows boots. The fact that is is the main competitor to bitlocker is just icing on the cake.\n\nConspiracy theory: Look at the VeraCrypt article on Wikipedia. Look at what \"they\" did to Truecrypt. Read the citations that give you the entire story of how that went down. Looks like \"they\" are doing it again.\n\n ",
              "score": 125,
              "created_utc": "2026-04-08 02:37:39",
              "is_submitter": true,
              "replies": [
                {
                  "id": "oexdy59",
                  "author": "Marble_Wraith",
                  "text": "> Reasonable theory #2: Microsoft simply does not trust anyone that doesn't have an employee badge to run code before Windows boots. The fact that is is the main competitor to bitlocker is just icing on the cake.\n\nYou're suggesting all games with kernel level anti-cheat are going to break?",
                  "score": 45,
                  "created_utc": "2026-04-08 02:59:02",
                  "is_submitter": false,
                  "replies": []
                },
                {
                  "id": "oezzk1d",
                  "author": "These-Apple8817",
                  "text": "My theory is that Microslop wants a backdoor which Veracrypt would not ever have.",
                  "score": 11,
                  "created_utc": "2026-04-08 14:14:25",
                  "is_submitter": false,
                  "replies": []
                }
              ]
            }
          ]
        },
        {
          "id": "oexfviq",
          "author": "WalterHenderson",
          "text": "I'm kind of a noob, so I'm a little confused. Does this mean that you can use VeraCrypt to encrypt for example an external drive, but not a partition of your laptop?",
          "score": 15,
          "created_utc": "2026-04-08 03:10:57",
          "is_submitter": false,
          "replies": [
            {
              "id": "oexpots",
              "author": "SadnessOutOfContext",
              "text": "TL;dr - pretty much. \n\nSounds like they can deploy \"traditional\" desktop programs (possibly with infuriating scary warnings on install) but not code that has to run before boot i.e., for decryption of full disk encryption. \n\nThis is bad because in June, anyone who has full disk encryption and hasn't made changes will have a real problem, at minimum.  \n\nHaven't read the article, am at work, so not yet 100% certain if you can just throw a USB stick at it, boot, and decrypt. ",
              "score": 18,
              "created_utc": "2026-04-08 04:15:31",
              "is_submitter": false,
              "replies": [
                {
                  "id": "oexv7bz",
                  "author": "Fear_The_Creeper",
                  "text": "...or possibly simply turn off secure boot, decrypt, and turn it back on. I am hoping that this gets resolved before we have to find out.",
                  "score": 6,
                  "created_utc": "2026-04-08 04:55:48",
                  "is_submitter": true,
                  "replies": []
                },
                {
                  "id": "of0d3u7",
                  "author": "WalterHenderson",
                  "text": "Thank you for the explanation!",
                  "score": 2,
                  "created_utc": "2026-04-08 15:16:18",
                  "is_submitter": false,
                  "replies": []
                }
              ]
            }
          ]
        },
        {
          "id": "oexjcsz",
          "author": "whatThePleb",
          "text": "Well, stop using Micro$lop.",
          "score": 57,
          "created_utc": "2026-04-08 03:33:03",
          "is_submitter": false,
          "replies": [
            {
              "id": "oexurpp",
              "author": "Fear_The_Creeper",
              "text": "CP/M is where it's at! [https://extkits.co.uk/product/pico-romwbw/](https://extkits.co.uk/product/pico-romwbw/)\n\n\n\n",
              "score": 9,
              "created_utc": "2026-04-08 04:52:32",
              "is_submitter": true,
              "replies": []
            },
            {
              "id": "of0qz3n",
              "author": "Yosyp",
              "text": "SecureBoot is part of the UEFI specification, Microsoft has nothing to do with it.\n\n\n\n\n\n  \n..... beside being one of the very few major signers that actively collaborates with motherboard manufacturers to implement their keys inside their firmware.\n\nYou can sign anything privately, provided you actually have access to UEFI and are capable of doing so.",
              "score": 3,
              "created_utc": "2026-04-08 16:18:12",
              "is_submitter": false,
              "replies": [
                {
                  "id": "of367ai",
                  "author": "h-v-smacker",
                  "text": ">  that actively collaborates with motherboard manufacturers to implement their keys inside their firmware.\n\nAh yes... _collaborates_... I can vividly imagine microsoft managers visiting the headquarters of various motherboard manufacturers and having long and heated discussions about whether or not to incorporate their cryptographic keys into firmware, and which terms would please the hardware manufacturer most. And the vendors are usually like _\"oh, we aren't all that sure it's a good idea... we might need to think a bit, ask our client base about what they want and such... please come back in a month or so\"_.",
                  "score": 2,
                  "created_utc": "2026-04-08 23:04:23",
                  "is_submitter": false,
                  "replies": []
                }
              ]
            }
          ]
        },
        {
          "id": "oey6pf8",
          "author": "Tail_sb",
          "text": "r/FuckMicrosoft\n\nr/Microslop\n\nr/Antitrust",
          "score": 24,
          "created_utc": "2026-04-08 06:29:48",
          "is_submitter": false,
          "replies": [
            {
              "id": "of251im",
              "author": "catlion",
              "text": "r/StallmanWasRight",
              "score": 3,
              "created_utc": "2026-04-08 20:03:00",
              "is_submitter": false,
              "replies": []
            }
          ]
        },
        {
          "id": "oewvs6y",
          "author": "xeoron",
          "text": "Now we pray to Copilot to fix these problems ",
          "score": 15,
          "created_utc": "2026-04-08 01:15:59",
          "is_submitter": false,
          "replies": []
        },
        {
          "id": "oey6sx7",
          "author": "Tail_sb",
          "text": "But can you still just self sign the Secure boot keys? ",
          "score": 3,
          "created_utc": "2026-04-08 06:30:37",
          "is_submitter": false,
          "replies": [
            {
              "id": "oezbod1",
              "author": "Fear_The_Creeper",
              "text": "Not even close to being a Windows expert, but I think that if it was that easy the developer of VeraCrypt would have done that.",
              "score": 2,
              "created_utc": "2026-04-08 12:09:23",
              "is_submitter": true,
              "replies": [
                {
                  "id": "oezwgjb",
                  "author": "Narrow_Trainer_5847",
                  "text": "No it means users can add the keys manually to continue using secure boot but it's a pain and some laptops (newer Lenovo business stuff iirc) don't allow custom keys. ",
                  "score": 8,
                  "created_utc": "2026-04-08 13:59:42",
                  "is_submitter": false,
                  "replies": []
                }
              ]
            }
          ]
        },
        {
          "id": "oez7pra",
          "author": "redit_handoff140",
          "text": "This is pretty much what they did with Atom Editor. \n\nE.E.E and extinguish the competition.",
          "score": 3,
          "created_utc": "2026-04-08 11:44:45",
          "is_submitter": false,
          "replies": []
        },
        {
          "id": "of35igz",
          "author": "h-v-smacker",
          "text": "Secure Boot was never about your security. It was always about Microsoft's control over the personal computers.",
          "score": 3,
          "created_utc": "2026-04-08 23:00:36",
          "is_submitter": false,
          "replies": []
        },
        {
          "id": "oey70w2",
          "author": "TechSupportIgit",
          "text": "This is a nothing burger, you needed to disable secure boot anyways to get boot disk encryption working properly. Secure boot support was poor anyways because you had to modify the secure boot keys of your system yourself.",
          "score": 1,
          "created_utc": "2026-04-08 06:32:32",
          "is_submitter": false,
          "replies": [
            {
              "id": "of25di0",
              "author": "diazeriksen07",
              "text": "You contradicted yourself. You don't need to disable secure boot. Like you said, you just add your own keys to it.",
              "score": 0,
              "created_utc": "2026-04-08 20:04:29",
              "is_submitter": false,
              "replies": [
                {
                  "id": "of29tf6",
                  "author": "TechSupportIgit",
                  "text": "...yes, and?\n\nDo you know how hard it is for even a power user to put their own keys into the motherboard's BIOS? I spent weeks trying to figure it out and threw my hands up in the air.\n\nThe most practical solution is to turn off secure boot entirely for VeraCrypt's boot disk encryption.",
                  "score": 1,
                  "created_utc": "2026-04-08 20:24:25",
                  "is_submitter": false,
                  "replies": []
                }
              ]
            }
          ]
        },
        {
          "id": "of54f8i",
          "author": "Fear_The_Creeper",
          "text": "The press is starting to take notice. And it's not just VeraCrypt. WireGuard and Windscribe have the same problem.\n\n* [**Developer of VeraCrypt encryption software says Windows users may face boot-up issues after Microsoft locked his account**](https://techcrunch.com/2026/04/08/veracrypt-encryption-software-windows-microsoft-lock-boot-issues/)\n* [**WireGuard VPN developer can’t ship software updates after Microsoft locks account**](https://techcrunch.com/2026/04/08/wireguard-vpn-developer-cant-ship-software-updates-after-microsoft-locks-account/)\n* [**Windscribe developer account suspended**](https://x.com/windscribecom/status/2041929519628443943)",
          "score": 1,
          "created_utc": "2026-04-09 06:38:19",
          "is_submitter": true,
          "replies": []
        },
        {
          "id": "oeyjv7m",
          "author": "Hot_Pomegranate_0019",
          "text": "I have a question dont you think you have to modify boot keys.",
          "score": 0,
          "created_utc": "2026-04-08 08:30:15",
          "is_submitter": false,
          "replies": []
        },
        {
          "id": "oex7t65",
          "author": "HurasmusBDraggin",
          "text": "Click bait?",
          "score": -21,
          "created_utc": "2026-04-08 02:22:20",
          "is_submitter": false,
          "replies": [
            {
              "id": "oexavfk",
              "author": "Fear_The_Creeper",
              "text": "Nope. Legitimate news about Microsoft screwing over a well-known open-source developer.",
              "score": 24,
              "created_utc": "2026-04-08 02:40:18",
              "is_submitter": true,
              "replies": [
                {
                  "id": "oexfsav",
                  "author": "[deleted]",
                  "text": "[deleted]",
                  "score": -4,
                  "created_utc": "2026-04-08 03:10:23",
                  "is_submitter": false,
                  "replies": []
                }
              ]
            }
          ]
        }
      ]
    },
    {
      "id": "1sc79aq",
      "title": "Europe builds Microsoft-alternative ‘Euro-Office’ to reclaim digital sovereignty",
      "subreddit": "opensource",
      "url": "https://tech.eu/2026/03/27/europe-builds-microsoft-compatible-euro-office-to-reclaim-digital-sovereignty/",
      "author": "deboo117",
      "created_utc": "2026-04-04 11:51:51",
      "score": 463,
      "num_comments": 51,
      "upvote_ratio": 0.97,
      "text": "[External Link]",
      "is_original_content": false,
      "link_flair_text": "Discussion",
      "permalink": "https://reddit.com/r/opensource/comments/1sc79aq/europe_builds_microsoftalternative_eurooffice_to/",
      "domain": "tech.eu",
      "is_self": false,
      "comments": [
        {
          "id": "oe9g5fw",
          "author": "TopHatTurtle97",
          "text": "Honestly, I think this will lead to a big boost for Linux, office editors on Linux aren’t the best atm. Your choice is between OnlyOffice, a nice and user friendly office suite but underdeveloped, or Libre office which is archaic and complicated and doesn’t mesh well with the most commonly used file formats.\n\nI know there are others, but really that’s the main two.",
          "score": 73,
          "created_utc": "2026-04-04 14:38:29",
          "is_submitter": false,
          "replies": [
            {
              "id": "oea22kr",
              "author": "kodos_der_henker",
              "text": "And it is still just those 2 as this is just an announcement that some European companies are planning to release a OnlyOffice fork under a new brand name",
              "score": 22,
              "created_utc": "2026-04-04 16:26:49",
              "is_submitter": false,
              "replies": [
                {
                  "id": "oea46fq",
                  "author": "TopHatTurtle97",
                  "text": "Yeah, but that means that OnlyOffice will get a massive amount of development work which should hopefully mean building out it’s features to give it more parity to a proper office suite.",
                  "score": 22,
                  "created_utc": "2026-04-04 16:37:21",
                  "is_submitter": false,
                  "replies": []
                }
              ]
            },
            {
              "id": "oeatssu",
              "author": "n-nnnn",
              "text": "Libre office is just awful compared to PowerPoint in my use case, and onlyoffice is Russian now apparently so this is actually a power move i think",
              "score": 2,
              "created_utc": "2026-04-04 18:42:06",
              "is_submitter": false,
              "replies": []
            },
            {
              "id": "oe9o98r",
              "author": "KestrelVO",
              "text": "There's also the chinese thing, WP Office or something like that... But it is not recommended as it is proprietary LOL",
              "score": 3,
              "created_utc": "2026-04-04 15:19:02",
              "is_submitter": false,
              "replies": []
            },
            {
              "id": "oeuotjq",
              "author": "The_Rusty_Wolf",
              "text": "Don't forget collabora. They have a self hosted version and I think they are open source.",
              "score": 1,
              "created_utc": "2026-04-07 18:34:02",
              "is_submitter": false,
              "replies": []
            },
            {
              "id": "oen30iv",
              "author": "whatThePleb",
              "text": "LibreOffice is completely fine.",
              "score": 1,
              "created_utc": "2026-04-06 16:37:26",
              "is_submitter": false,
              "replies": []
            }
          ]
        },
        {
          "id": "oe9437z",
          "author": "paxil0r",
          "text": "„Hello Brussels. This is your beloved lobby groups. Just wanted to let you know you won’t be doing that. Thanks.“",
          "score": 31,
          "created_utc": "2026-04-04 13:33:36",
          "is_submitter": false,
          "replies": [
            {
              "id": "oe9s488",
              "author": "TopHatTurtle97",
              "text": "Generally speaking, I think the EU has shown that it’s willing to work against lobbying interests, if lobbying worked with them, they wouldn’t have forced Apple to use USB C ports and to allow app side-loading. Plus the anti-monopoly legislation against the Play Store and Apple App Store.\n\nPretty sure the EU’s need to be independent of US influence in their digital infrastructure outweighs any lobbying interests.",
              "score": 19,
              "created_utc": "2026-04-04 15:38:01",
              "is_submitter": false,
              "replies": []
            },
            {
              "id": "oea0p2d",
              "author": "TemporarySun314",
              "text": "i mean that is not an project by the state. its a project by multiple european companies and non-profit organizations. they have their own interests in that and wont let their profits become ruined by US tech companies ",
              "score": 8,
              "created_utc": "2026-04-04 16:20:02",
              "is_submitter": false,
              "replies": [
                {
                  "id": "oee0md9",
                  "author": "Poppod",
                  "text": "The problem is not the business, the only problem is the current dictatorship. Market economy is the best way, with monopoly there is no market economy.",
                  "score": -2,
                  "created_utc": "2026-04-05 06:10:50",
                  "is_submitter": false,
                  "replies": []
                }
              ]
            }
          ]
        },
        {
          "id": "oeerdxg",
          "author": "lamalasx",
          "text": "More like \"europe forked an open source project then claimed it as their own with 0 contribution\". I bet someone is pocketing a lot of money for this.",
          "score": 9,
          "created_utc": "2026-04-05 10:15:35",
          "is_submitter": false,
          "replies": [
            {
              "id": "oeineoi",
              "author": "ramonchow",
              "text": "I tried to get this app and always ended up in some company website so I feel this \"Europe builds\" is nothing more than a marketing stunt to capitalize the current falling appart from the US.",
              "score": 1,
              "created_utc": "2026-04-05 22:59:05",
              "is_submitter": false,
              "replies": []
            }
          ]
        },
        {
          "id": "oeeqhy5",
          "author": "RobotToaster44",
          "text": "the word \"builds\" is doing a lot of heavy lifting here, since all they did was fork and existing program.",
          "score": 4,
          "created_utc": "2026-04-05 10:07:30",
          "is_submitter": false,
          "replies": []
        },
        {
          "id": "oec6pcn",
          "author": "bigbarba",
          "text": "Apparently the difficult part is not the office suite but the tightly knitted full ecosystem of software, operating system and very convenient tools to manage identities and access management and all the employees' hardware in large companies.\n\nLooks like there is no easy swap-in alternatives to the likes of intune. If there was it would be costly to switch but manageable, instead leaving Microsoft would currently require to choose a lot of different components for each required function and setting up or even developing custom integrations between them.\n\nAt least this is what I understood from the sysadmins...",
          "score": 6,
          "created_utc": "2026-04-04 22:55:14",
          "is_submitter": false,
          "replies": [
            {
              "id": "oedrin3",
              "author": "mcilrain",
              "text": "If this were true lobbyists wouldn't be trying to prevent competition.",
              "score": 1,
              "created_utc": "2026-04-05 04:55:30",
              "is_submitter": false,
              "replies": []
            }
          ]
        },
        {
          "id": "oedudpl",
          "author": "RALF663",
          "text": "There is also office.eu coming ",
          "score": 3,
          "created_utc": "2026-04-05 05:18:05",
          "is_submitter": false,
          "replies": []
        },
        {
          "id": "oeg6v9d",
          "author": "techiee_",
          "text": "the real test is adoption outside of government systems. LibreOffice has been \"good enough\" for years but people still default to Word because of habits and compatibility. Euro-Office will need to absolutely nail .docx/.xlsx interop or it'll just become another tool that IT depts deploy and users immediately hate",
          "score": 3,
          "created_utc": "2026-04-05 15:34:37",
          "is_submitter": false,
          "replies": []
        },
        {
          "id": "oee6jfn",
          "author": "ImBadAtJumping",
          "text": "Why not Libre Office and [LibreOffice Online](https://www.libreoffice.org/download/libreoffice-online/) ([Collabora Online](https://www.collaboraonline.com/collabora-online/))?",
          "score": 5,
          "created_utc": "2026-04-05 07:02:10",
          "is_submitter": false,
          "replies": [
            {
              "id": "oeekijr",
              "author": "deboo117",
              "text": "My thoughts exactly. Not a single mention of the biggest open source project in that space even.",
              "score": 5,
              "created_utc": "2026-04-05 09:11:22",
              "is_submitter": true,
              "replies": [
                {
                  "id": "oehb8sv",
                  "author": "eldelacajita",
                  "text": "To be fair, in the Github repo they do mention it.\n\n\nTo keep being fair, they don't say much about it. ",
                  "score": 1,
                  "created_utc": "2026-04-05 18:48:18",
                  "is_submitter": false,
                  "replies": []
                }
              ]
            },
            {
              "id": "oeez69c",
              "author": "Left-Set950",
              "text": "I honestly think the concept of open source sounds scary to politicians. Also they want to sound they did something about it. For this is would be better for them to just fork libreoffice and change the logo to the EU",
              "score": 2,
              "created_utc": "2026-04-05 11:22:16",
              "is_submitter": false,
              "replies": [
                {
                  "id": "oefpd9g",
                  "author": "temporarilyyours",
                  "text": "The Indian judicial system managed to [turn almost entirely to a customised UBUNTU distro.](https://www.pib.gov.in/PressReleasePage.aspx?PRID=2042986&reg=3&lang=2) \n\nhttps://basti.dcourts.gov.in/document-category/softwares/",
                  "score": 1,
                  "created_utc": "2026-04-05 14:08:04",
                  "is_submitter": false,
                  "replies": []
                }
              ]
            },
            {
              "id": "oeinzus",
              "author": "g_shogun",
              "text": "LibreOffice has been dead since they kicked out Collabora.",
              "score": 0,
              "created_utc": "2026-04-05 23:02:20",
              "is_submitter": false,
              "replies": [
                {
                  "id": "oen388i",
                  "author": "whatThePleb",
                  "text": "It isn't.",
                  "score": 1,
                  "created_utc": "2026-04-06 16:38:27",
                  "is_submitter": false,
                  "replies": []
                }
              ]
            }
          ]
        },
        {
          "id": "oeda3dg",
          "author": "HurasmusBDraggin",
          "text": "Why not just contribute to LibreOffice? Dumb. Waste.",
          "score": 6,
          "created_utc": "2026-04-05 02:52:16",
          "is_submitter": false,
          "replies": [
            {
              "id": "oeio7wb",
              "author": "g_shogun",
              "text": "It's a dead project.",
              "score": 0,
              "created_utc": "2026-04-05 23:03:36",
              "is_submitter": false,
              "replies": [
                {
                  "id": "oeioj1e",
                  "author": "HurasmusBDraggin",
                  "text": "LibreOffice dead? 304 please!",
                  "score": 2,
                  "created_utc": "2026-04-05 23:05:19",
                  "is_submitter": false,
                  "replies": []
                }
              ]
            }
          ]
        },
        {
          "id": "oee9a63",
          "author": "Sea_Cloud1089",
          "text": "seriously ???",
          "score": 2,
          "created_utc": "2026-04-05 07:26:35",
          "is_submitter": false,
          "replies": []
        },
        {
          "id": "oeg5exz",
          "author": "techiee_",
          "text": "honestly the timing makes sense. after the whole US cloud dependency conversations happening in EU governments, they had to do something. \n\n\n\nthe real question is whether this actually gets adopted or just becomes another project that exists on paper. LibreOffice has been around forever and government orgs still default to MS Office lol. hope this one actually has proper funding and isn't just a rebranded fork with a flag slapped on it",
          "score": 2,
          "created_utc": "2026-04-05 15:27:35",
          "is_submitter": false,
          "replies": [
            {
              "id": "oehbp0g",
              "author": "eldelacajita",
              "text": "Looking at the companies that are behind this fork, lead by Nextcloud, I'd say the prospect is good so far. ",
              "score": 1,
              "created_utc": "2026-04-05 18:50:32",
              "is_submitter": false,
              "replies": []
            }
          ]
        },
        {
          "id": "oehcbml",
          "author": "eldelacajita",
          "text": "I hope:\n\n\n- Thet take it seriously and keep it under active development.\n\n- They don't break it or make it less reliable.\n- They find a better name for it.\n- They eventually cover all applications and not just the online one. ",
          "score": 2,
          "created_utc": "2026-04-05 18:53:39",
          "is_submitter": false,
          "replies": []
        },
        {
          "id": "oennj10",
          "author": "hyakkymaru",
          "text": "Yeah no one is gonna use this mega corporate project with 0 open source attribution and growth ",
          "score": 2,
          "created_utc": "2026-04-06 18:08:54",
          "is_submitter": false,
          "replies": []
        },
        {
          "id": "oer8nvy",
          "author": "Stitch10925",
          "text": "Wonder how much tracking and stuff they'll put in it.\n\nKnowing that the EU is a control-hungry, we-want-to-know-everything-about-everybody, and freedom taking organization, there has to be a reason why they are now suddenly actively rolling out \"EU\" software. First the EU AI-models, now an EU office software, the core code for Digital ID compatibility, etc. \n\nI don't trust it one bit. ",
          "score": 2,
          "created_utc": "2026-04-07 06:30:51",
          "is_submitter": false,
          "replies": []
        },
        {
          "id": "oei7q1z",
          "author": "elhaytchlymeman",
          "text": "Based on Russian development",
          "score": 1,
          "created_utc": "2026-04-05 21:32:50",
          "is_submitter": false,
          "replies": []
        },
        {
          "id": "oekip9k",
          "author": "CatEatsDogs",
          "text": "Huh? Its like \"nextcloud is a freedom, digital sovereignty\" etc, and then their Talk android application threats call as message with corresponding notification.\nSo now they just forking and rebranding OnlyOffice, get money in their poket and leave the new \"euro\" software under open-source maintanence of one or two software engineers.",
          "score": 0,
          "created_utc": "2026-04-06 06:34:43",
          "is_submitter": false,
          "replies": []
        },
        {
          "id": "oe8omn5",
          "author": "lKrauzer",
          "text": "The only problem is that they are trying to force OnlyOffice to break their licencing by forcing branding on it. EU should learn how to fork.",
          "score": -40,
          "created_utc": "2026-04-04 11:58:06",
          "is_submitter": false,
          "replies": [
            {
              "id": "oe8psqb",
              "author": "AnonomousWolf",
              "text": "I struggle to understand what you're saying.\n\nOnlyOffice put a illegitimate clause in their liscence, that is not allowed in AGPL3, so Euro-Office is in the clear. ",
              "score": 41,
              "created_utc": "2026-04-04 12:06:11",
              "is_submitter": false,
              "replies": []
            },
            {
              "id": "oe8rlvq",
              "author": "TemporarySun314",
              "text": "The Russian company behind has an let's call it \"unique' way to interpret the AGPL and does it in a way that would make forks impossible.\n\nBut I'm sure that can be figured out in court who is in right",
              "score": 19,
              "created_utc": "2026-04-04 12:18:30",
              "is_submitter": false,
              "replies": [
                {
                  "id": "oeehlur",
                  "author": "cookiengineer",
                  "text": "> The Russian company behind has an let's call it \"unique' way to interpret the AGPL and does it in a way that would make forks impossible.\n\nhttps://github.com/ONLYOFFICE\n\nIn case they change the legal notice, this is the archive link:\n\nhttps://web.archive.org/web/20260403124051/https://github.com/ONLYOFFICE\n\nMy take:\n\nSo much legal drama. It's like a weaponization attempt of the AGPL3 by abusing trademark law, and the AGPL is one of the most libre licenses ever written. No idea why they are this rogue, as it's impossible to satisfy their additions.\n\nOne could argue that they use the term \"AGPL\" as a brand to make it look like they're open source, which technically would be worth a lawsuit for fraud.\n\nI mean I get it, protection of company IP and all, and it's a hard market to compete in - especially with Microsoft and others pushing hard. But this kind of legal notice makes me not want to fund that project. If they would just AGPL3 everything and have their support-licensed Enterprise editions, then I'd be totally fine with it; as that's their way to cover development costs.",
                  "score": 1,
                  "created_utc": "2026-04-05 08:43:49",
                  "is_submitter": false,
                  "replies": []
                }
              ]
            },
            {
              "id": "oe8vctk",
              "author": "SimiKusoni",
              "text": "For those curious the relevant section of their license is [here](https://github.com/ONLYOFFICE/DocumentServer/blob/master/LICENSE.txt#L376) (emphasis mine):\n\n>All other non-permissive additional terms are considered \"further restrictions\" within the meaning of section 10. If the Program as you received it, or any part of it, contains a notice stating that it is governed by this License along with a term that is a further restriction, **you may remove that term**.\n\nThe permitted further restrictions are directly above this paragraph in the license. The closest fit is that it allows devs to require preservation of specific and reasonable legal notices or author attribution, but a logo isn't author attribution and if you are also not granting the rights to preserve said logo it isn't reasonable either.\n\nBasically OpenOffice devs should have gone with a different license, namely a source-available license instead of a true open source one. They've basically screwed themselves by trying to play silly games without actually reading the license they added impossible to satisfy terms to.",
              "score": 9,
              "created_utc": "2026-04-04 12:42:41",
              "is_submitter": false,
              "replies": []
            }
          ]
        }
      ]
    },
    {
      "id": "1sapvbc",
      "title": "FAKKU DMCAed one of the most popular gallery downloader, gallery-dl, and forced the maintainer to remove support for hentai sites. Affected sites: NHentai, E-Hentai/ExHentai, hitomi.la, Hentai Foundry, HentaiHand, HentaiNexus, Schale Network, HDoujin",
      "subreddit": "opensource",
      "url": "https://github.com/mikf/gallery-dl/discussions/9304",
      "author": "rexyuan",
      "created_utc": "2026-04-02 18:40:55",
      "score": 146,
      "num_comments": 12,
      "upvote_ratio": 0.97,
      "text": "[External Link]",
      "is_original_content": false,
      "link_flair_text": "Promotional",
      "permalink": "https://reddit.com/r/opensource/comments/1sapvbc/fakku_dmcaed_one_of_the_most_popular_gallery/",
      "domain": "github.com",
      "is_self": false,
      "comments": [
        {
          "id": "odzdmv4",
          "author": "KatWithTalent",
          "text": "The width of what they are DMCAing is so flakey. There's a reason people avoided using their site to begin with...it became crud. And behavior like this will turn even more people away. They pulled a Crunchyroll. They started as a piracy site!\n\nThey can't win against the websites so they are just scaring who they can easily on GitHub.",
          "score": 52,
          "created_utc": "2026-04-03 00:11:10",
          "is_submitter": false,
          "replies": []
        },
        {
          "id": "ody1vkx",
          "author": "furculture",
          "text": "The are too FAKKed up of a company. ",
          "score": 25,
          "created_utc": "2026-04-02 20:03:33",
          "is_submitter": false,
          "replies": []
        },
        {
          "id": "odyxppc",
          "author": "vinceh121",
          "text": "Seems like a similar case to the RIAA DMCAing youtube-dl. After the pushback GitHub reinstated that repo",
          "score": 26,
          "created_utc": "2026-04-02 22:42:21",
          "is_submitter": false,
          "replies": [
            {
              "id": "oe524tf",
              "author": "korewatori",
              "text": "We won't see similar pushback on this because people hate porn",
              "score": 12,
              "created_utc": "2026-04-03 20:44:38",
              "is_submitter": false,
              "replies": []
            }
          ]
        },
        {
          "id": "oe1scgp",
          "author": "Xtrems876",
          "text": "I find it funny that sites that started from piracy are DMCAing others.\n\nThe piracy subreddit is full of people justifying the morality of piracy every other day, but these sites don't hide at all that they just want free stuff and they have no interest in morality :D becoming \"legitimate\" was just a move from \"free stuff\" to \"free money to spend on paid stuff\".\n\nReminds me of all those gangs in eastern europe from the 90s that are now doing legitimate business once they got the capital to do that from criminal activity.",
          "score": 14,
          "created_utc": "2026-04-03 10:48:57",
          "is_submitter": false,
          "replies": []
        },
        {
          "id": "ody9cbx",
          "author": "wtdawson",
          "text": "Over some Python scripts is crazy",
          "score": 26,
          "created_utc": "2026-04-02 20:38:51",
          "is_submitter": false,
          "replies": []
        },
        {
          "id": "oe87r8o",
          "author": "whatThePleb",
          "text": "Ironic considering that Fakku was once an illegal manga piracy site.",
          "score": 7,
          "created_utc": "2026-04-04 09:37:21",
          "is_submitter": false,
          "replies": []
        },
        {
          "id": "oebnylw",
          "author": "temmiesayshoi",
          "text": "What? That doesn't even logically parse. The ***actual*** sites themselves (ehentai, rule34, whatever) would have a better DMCA case to demand gallery-dl block downloads from them. (and even that's tenuous since they don't actually own the content that's uploaded to them, so the only things that gallery-dl downloads isn't their IP)\n\nThis would be like seeing someone rob a 7/11 for a can of sprite using a glock, and then sprite trying to sue 7/11 to ban glock owners from going to their store. It's not just unfounded, it's incomprehensible. You could at least vaguely follow the logic if 7/11 said \"due to past events we are hereby making 7/11 locations gun-free zones\" (though of course then you get into the more loaded questions of whether that'd even work, whether it'd have the intended effects, etc.) but what does owning a glock have to do with drinking sprite or going to 7/11 more generally? Sure, *hypothetically* a glock owner *might* misuse their weapon to rob a 7/11 and steal a sprite, but A : that doesn't in any way imply glock owners shouldn't be able to drink sprite more broadly, B : it doesn't even begin to imply they shouldn't be able to legally shop at 7/11 and buy literally anything other than a sprite, and C : even if it did... why the hell are you suing 7/11 to try to do it?!\n\nDMCAing a project, to prevent them from interacting with a completely different company's services doesn't even make sense in the first place. If these sites are hosting your IP... then DMCA ***those*** sites! Why would you ever have a legal basis for making company A stop being able to interact with company B on the basis of a DMCA?\n\nUnless I'm horribly misunderstanding something, (which *is* possible) this feels like a legal request filed by people with absolutely no understanding of what the DMCA is on even a conceptual level.",
          "score": 5,
          "created_utc": "2026-04-04 21:13:29",
          "is_submitter": false,
          "replies": [
            {
              "id": "oec4co5",
              "author": "rexyuan",
              "text": "They DEFINITELY know what a DMCA is. This FAKKU company is just notorious for DMCA rampage. If you search in lumendatabase.org you can see they have filed almost 20k DMCA notices in the past (8120 directly+11517 via their DMCA handler)",
              "score": 5,
              "created_utc": "2026-04-04 22:42:02",
              "is_submitter": true,
              "replies": [
                {
                  "id": "oelpg8f",
                  "author": "siedenburg2",
                  "text": "It should be forbidden for copyright holders to file DMCA if over 50% of them are misuse. For that to be able again they should have to take the case to court and win.",
                  "score": 1,
                  "created_utc": "2026-04-06 12:30:47",
                  "is_submitter": false,
                  "replies": []
                }
              ]
            }
          ]
        }
      ]
    },
    {
      "id": "1sbyff9",
      "title": "Will we ever have a codec that doesn't cost companies licensing fees?",
      "subreddit": "opensource",
      "url": "https://www.reddit.com/r/opensource/comments/1sbyff9/will_we_ever_have_a_codec_that_doesnt_cost/",
      "author": "Relative-Category-64",
      "created_utc": "2026-04-04 03:25:45",
      "score": 91,
      "num_comments": 40,
      "upvote_ratio": 0.97,
      "text": "I'm a layman when it comes to this. I find it incredible that Avanci etc... can claim royalty fees for ideas patented decades ago. ",
      "is_original_content": false,
      "link_flair_text": "Discussion",
      "permalink": "https://reddit.com/r/opensource/comments/1sbyff9/will_we_ever_have_a_codec_that_doesnt_cost/",
      "domain": "self.opensource",
      "is_self": true,
      "comments": [
        {
          "id": "oe79nah",
          "author": "dodexahedron",
          "text": "Patents expire. Software patents get 20 years, in the US, and aren't susceptible to the monkey business that, e.g., drug companies do to artificially extend their patents (like changing something about how a drug is administered).\n\nCodecs are algorithms: math. Math is math, so once the algorithm is out there, it's out there and can be duplicated after expiry.\n\nNow, the *content* is of course another story, because of copyright. But that's an entirely separate issue from codecs, and one for which the regulatory capture ship sailed long ago, unfortunately.\n\nTrade secrets, though, are always part of it. Nobody ever patents the entire thing, end to end.",
          "score": 50,
          "created_utc": "2026-04-04 04:37:45",
          "is_submitter": false,
          "replies": [
            {
              "id": "oe8rkdt",
              "author": "hxtk3",
              "text": "> Patents expire. Software patents get 20 years, in the US, and aren't susceptible to the monkey business that, e.g., drug companies do to artificially extend their patents (like changing something about how a drug is administered).\n\nThe IBM patent on Adaptive Replacement Caching got an extension recently when it was due to expire.\n",
              "score": 8,
              "created_utc": "2026-04-04 12:18:13",
              "is_submitter": false,
              "replies": []
            }
          ]
        },
        {
          "id": "oe7izgg",
          "author": "NicholasVinen",
          "text": "Aren't all Vorbis codecs, including Theora, license free?",
          "score": 37,
          "created_utc": "2026-04-04 05:52:56",
          "is_submitter": false,
          "replies": [
            {
              "id": "oe7jgpp",
              "author": "ivosaurus",
              "text": "And Opus is an extension on that",
              "score": 26,
              "created_utc": "2026-04-04 05:57:00",
              "is_submitter": false,
              "replies": []
            }
          ]
        },
        {
          "id": "oe7iy1i",
          "author": "Yugen42",
          "text": "VP8 is one such codec, other than that we have to wait until courts decide regarding AV1. None of this affects individuals though afaik.",
          "score": 16,
          "created_utc": "2026-04-04 05:52:36",
          "is_submitter": false,
          "replies": []
        },
        {
          "id": "oe72b6z",
          "author": "Prestigious_Boat_386",
          "text": "Probably not. There are way too many patented simple ideas in computer science. Every efficient codec would need to include a variant of many patented algorithms because they're way too simple and should never have been patented in the first place. ",
          "score": 17,
          "created_utc": "2026-04-04 03:44:26",
          "is_submitter": false,
          "replies": [
            {
              "id": "oe7v36d",
              "author": "TemporarySun314",
              "text": "That's why I find it good that you can't patent software or pure algorithms in the EU. \nOnly when they are part of a larger invention.",
              "score": 9,
              "created_utc": "2026-04-04 07:39:45",
              "is_submitter": false,
              "replies": [
                {
                  "id": "oe7ysrd",
                  "author": "voidvector",
                  "text": "It goes both ways. You can \"patent\" fonts in EU, but you cannot \"patent\" fonts in US.\n\nhttps://en.wikipedia.org/wiki/Intellectual_property_protection_of_typefaces",
                  "score": 3,
                  "created_utc": "2026-04-04 08:13:23",
                  "is_submitter": false,
                  "replies": []
                }
              ]
            },
            {
              "id": "oe7326b",
              "author": "belhill1985",
              "text": "Okay, I’ll bite, tell me how WPP is a “simple idea”",
              "score": -12,
              "created_utc": "2026-04-04 03:49:38",
              "is_submitter": false,
              "replies": [
                {
                  "id": "oe74oj3",
                  "author": "Marble_Wraith",
                  "text": "How impertenant! I hereby sentence you to 12 hours in the patented ass kicking machine!\n\nhttps://patents.google.com/patent/US6293874",
                  "score": 17,
                  "created_utc": "2026-04-04 04:00:57",
                  "is_submitter": false,
                  "replies": []
                },
                {
                  "id": "oe746j9",
                  "author": "dpdxguy",
                  "text": "He didn't say \"every software patent is a simple idea.\" He said many software patents are simple ideas. And that's true.\n\nI used to work with a guy who got a patent for using binary search to find indexed data on a magnetic tape. None of us engineers thought it was novel enough to be patented. The lawyers and patent office disagreed.",
                  "score": 14,
                  "created_utc": "2026-04-04 03:57:26",
                  "is_submitter": false,
                  "replies": []
                }
              ]
            }
          ]
        },
        {
          "id": "oe93m3m",
          "author": "Bour_",
          "text": "[AV1](https://en.wikipedia.org/wiki/AV1)",
          "score": 5,
          "created_utc": "2026-04-04 13:30:53",
          "is_submitter": false,
          "replies": []
        },
        {
          "id": "oe8b2dq",
          "author": "Julian_1_2_3_4_5",
          "text": "oh if legislators cared about consumers, or smaller software companies they would have made software patents illegal, especially on formats or standarts a long time ago.",
          "score": 3,
          "created_utc": "2026-04-04 10:07:51",
          "is_submitter": false,
          "replies": []
        },
        {
          "id": "oe7v5ud",
          "author": "IchLiebeKleber",
          "text": "Codecs for what? For video we already have Ogg Theora and WebM.",
          "score": 3,
          "created_utc": "2026-04-04 07:40:27",
          "is_submitter": false,
          "replies": []
        },
        {
          "id": "oe9kzrr",
          "author": "kitsumed",
          "text": "Multiples compagny regrouped themself and created/financed AV1. No royalty, fully FOSS. From memorie, I think Intel and Netflix are part of the compagny that participed. But you should search online.",
          "score": 2,
          "created_utc": "2026-04-04 15:02:53",
          "is_submitter": false,
          "replies": []
        },
        {
          "id": "oe9qww3",
          "author": "electromage",
          "text": "Yes, there are open source codecs like x264, x265, VP8, VP9, AV1, Theora, etc.",
          "score": 2,
          "created_utc": "2026-04-04 15:32:06",
          "is_submitter": false,
          "replies": [
            {
              "id": "oe9rckh",
              "author": "Relative-Category-64",
              "text": "Avanci getting licensing fees from these. They say the  basic ideas behind compression are patented. ",
              "score": 2,
              "created_utc": "2026-04-04 15:34:15",
              "is_submitter": true,
              "replies": []
            }
          ]
        },
        {
          "id": "oe7zj3s",
          "author": "voidvector",
          "text": "Plenty but you gotta convince publishers and device manufacturers to use them. \n\n* Publishers - Well good luck with this one. They would only give you DRM free content if it makes them more money (e.g. Apple use it as marketing), which is rare. \n* Device manufacturers - The larger ones are often the ones owning those patents, so they want smaller players to pay them royalty.",
          "score": 1,
          "created_utc": "2026-04-04 08:20:09",
          "is_submitter": false,
          "replies": [
            {
              "id": "oe8shaj",
              "author": "hxtk3",
              "text": "DRM is usually at the media container level or higher rather than the codec level.",
              "score": 2,
              "created_utc": "2026-04-04 12:24:18",
              "is_submitter": false,
              "replies": []
            },
            {
              "id": "oe9hy2l",
              "author": "Relative-Category-64",
              "text": "From what I understand, regardless of the new codec, it would be using ideas that have already been patented. Even if extremely basic in decades old simple ideas",
              "score": 1,
              "created_utc": "2026-04-04 14:47:38",
              "is_submitter": true,
              "replies": [
                {
                  "id": "oeadej5",
                  "author": "voidvector",
                  "text": "The wheel was invented thousands of years ago, but automobile patent might be minor stuff like using cartain material in certain shape as suspension. Same applies to codec patents.",
                  "score": 1,
                  "created_utc": "2026-04-04 17:21:54",
                  "is_submitter": false,
                  "replies": []
                }
              ]
            }
          ]
        },
        {
          "id": "oesy4o9",
          "author": "Alarmed-Plastic-4544",
          "text": "Cisco did the world a solid with OpenH264, a reverse-engineered version of H264 where they pay a fixed royalty and make it available with a BSD license. The quality however does not hold a candle to x264...",
          "score": 1,
          "created_utc": "2026-04-07 13:56:31",
          "is_submitter": false,
          "replies": []
        },
        {
          "id": "oe72w3u",
          "author": "belhill1985",
          "text": "I find it incredible that people thought they could steal ideas patented five years earlier and get away with it!",
          "score": -9,
          "created_utc": "2026-04-04 03:48:27",
          "is_submitter": false,
          "replies": []
        },
        {
          "id": "oe77clf",
          "author": "AdreKiseque",
          "text": "I'm not too in the know what is this post about ",
          "score": -5,
          "created_utc": "2026-04-04 04:20:22",
          "is_submitter": false,
          "replies": []
        }
      ]
    },
    {
      "id": "1sakqsj",
      "title": "Euro-Office, ONLYOFFICE, and their licensing dispute",
      "subreddit": "opensource",
      "url": "https://blog.ensko.at/2026/04/02/euro-office/",
      "author": "Silly-Freak",
      "created_utc": "2026-04-02 15:35:21",
      "score": 72,
      "num_comments": 42,
      "upvote_ratio": 0.95,
      "text": "[External Link]",
      "is_original_content": false,
      "link_flair_text": null,
      "permalink": "https://reddit.com/r/opensource/comments/1sakqsj/eurooffice_onlyoffice_and_their_licensing_dispute/",
      "domain": "blog.ensko.at",
      "is_self": false,
      "comments": [
        {
          "id": "odwfqt0",
          "author": "AutoModerator",
          "text": "Posts relating to the [Russo-Ukrainian War](https://en.wikipedia.org/wiki/Russo-Ukrainian_War) have not resulted in on-topic or constructive discussion. We will be using additional scrutiny enforcing on-topic discussion in these comments.\n\nPlease ensure that comments and replies relate directly to the open source community and people's participation in it.\n\n\n*I am a bot, and this action was performed automatically. Please [contact the moderators of this subreddit](/message/compose/?to=/r/opensource) if you have any questions or concerns.*",
          "score": 1,
          "created_utc": "2026-04-02 15:35:21",
          "is_submitter": false,
          "replies": []
        },
        {
          "id": "odzqd1y",
          "author": "webfork2",
          "text": "... but with controversial additional terms that may either be \"further restrictions\"\n\nReally wish posts about this would just list out the restrictions.  It's very simple:\n\n> Pursuant to Section 7 § 3(b) of the GNU AGPL you must retain the original ONLYOFFICE logo in the upper left corner of the user interface when distributing the software.\n\n> Pursuant to Section 7 § 3(e) we decline to grant you any rights under trademark law for use of our trademarks.\n\nIn short you can't use our trademarks (which is very normal in open source) but you have to use our trademarked image (not normal).  Whether or not it's enforceable, it's plainly a contradictory request to prevent forking.",
          "score": 21,
          "created_utc": "2026-04-03 01:26:05",
          "is_submitter": false,
          "replies": [
            {
              "id": "oe1pe50",
              "author": "ryker7777",
              "text": "Logo can be very small though ... ;-)\n",
              "score": 8,
              "created_utc": "2026-04-03 10:25:24",
              "is_submitter": false,
              "replies": [
                {
                  "id": "oe49rtn",
                  "author": "webfork2",
                  "text": "lol -- if they ask me I'll definitely suggest that :)",
                  "score": 3,
                  "created_utc": "2026-04-03 18:28:53",
                  "is_submitter": false,
                  "replies": []
                }
              ]
            },
            {
              "id": "oejs6g1",
              "author": "kettal",
              "text": "catch 22",
              "score": 2,
              "created_utc": "2026-04-06 03:04:50",
              "is_submitter": false,
              "replies": []
            }
          ]
        },
        {
          "id": "oe1vxmq",
          "author": "AnonomousWolf",
          "text": "Clause 7b of ONLYOFFICE's license is invalid, as you aren't allowed to put restrictions on AGPL3  \n  \n[https://github.com/Euro-Office/DocumentServer/issues/44](https://github.com/Euro-Office/DocumentServer/issues/44)",
          "score": 14,
          "created_utc": "2026-04-03 11:15:42",
          "is_submitter": false,
          "replies": []
        },
        {
          "id": "odxcuzx",
          "author": "Substantial_Tea_5731",
          "text": "I found this: [https://github.com/Euro-Office/DocumentServer/issues/44](https://github.com/Euro-Office/DocumentServer/issues/44)\n\nLooks like in US there was already similar case and it was decided, that you cant just remove the additional restrictions added to AGPL.",
          "score": 9,
          "created_utc": "2026-04-02 18:06:10",
          "is_submitter": false,
          "replies": [
            {
              "id": "oe12p2c",
              "author": "Shinucy",
              "text": "This need not necessarily be the case here. OnlyOffice deliberately stipulates in one clause that the logo and trademarks must be retained when creating a fork, whilst in the very next clause they categorically prohibit the use of their logo in any circumstances. This creates a deliberate contradiction that is impossible to fulfill in any conceivable scenario and ultimately prevents the creation of a fork.\n\nIf the matter goes to court, I think any logical judge would point out such an obvious legal foul play.",
              "score": 10,
              "created_utc": "2026-04-03 07:04:41",
              "is_submitter": false,
              "replies": [
                {
                  "id": "oe1pukl",
                  "author": "Substantial_Tea_5731",
                  "text": "If its impossible to fulfill, then you simply dont have a right to fork it.\n\nI could make a license that says \"anyone forking my work must be able to travel faster than light in vacuum\". Its impossible but legal. You simply cant fork my work unless you can do the impossible. Which is basically a longer way to say \"you cant fork my work\".",
                  "score": -2,
                  "created_utc": "2026-04-03 10:29:12",
                  "is_submitter": false,
                  "replies": []
                }
              ]
            },
            {
              "id": "odxpfuy",
              "author": "Silly-Freak",
              "text": "Oh, thanks for this heads-up! I'll have to add this to the post in a future edit; might take me a few days though...",
              "score": 3,
              "created_utc": "2026-04-02 19:04:37",
              "is_submitter": true,
              "replies": []
            },
            {
              "id": "oe8wib2",
              "author": "mattiasso",
              "text": "You are forgetting that other parts of the license they adopted, AGPLv3, void those restrictive clauses. So they are LEGALLY void.",
              "score": 3,
              "created_utc": "2026-04-04 12:49:47",
              "is_submitter": false,
              "replies": []
            }
          ]
        },
        {
          "id": "oe1n0ma",
          "author": "generichuman27ABF9",
          "text": "Considering the Russian government and corporations blatantly ignore western copyright law every day, I think it's overdue for us to do the same. Especially when the license itself makes no sense at all and is clearly aimed at making forks impossible - the cornerstone of opensource. ",
          "score": 6,
          "created_utc": "2026-04-03 10:05:41",
          "is_submitter": false,
          "replies": [
            {
              "id": "oe2iobw",
              "author": "pydry",
              "text": "It's made by a company based in Latvia.",
              "score": 2,
              "created_utc": "2026-04-03 13:35:09",
              "is_submitter": false,
              "replies": [
                {
                  "id": "oe4th7j",
                  "author": "Present-Savings-2380",
                  "text": "It’s originally a Russian company. ",
                  "score": 3,
                  "created_utc": "2026-04-03 20:02:57",
                  "is_submitter": false,
                  "replies": []
                }
              ]
            }
          ]
        },
        {
          "id": "odxt5qv",
          "author": "trisul-108",
          "text": ">or ONLYOFFICE's supposed current/former Russia connections. The latter one is a can of worm I was not interested opening.\n\nNevertheless, we simply cannot build a Euro-Office based on Russian connections using Russian developers. It would be a dead end story.",
          "score": 1,
          "created_utc": "2026-04-02 19:22:12",
          "is_submitter": false,
          "replies": []
        }
      ]
    },
    {
      "id": "1sbaq1u",
      "title": "Euro-Office: European industry initiative launches office suite",
      "subreddit": "opensource",
      "url": "https://nextcloud.com/blog/press_releases/industry-initiative-launches-euro-office-as-true-sovereign-office-suite/",
      "author": "AnonomousWolf",
      "created_utc": "2026-04-03 11:15:26",
      "score": 39,
      "num_comments": 12,
      "upvote_ratio": 0.92,
      "text": "[External Link]",
      "is_original_content": false,
      "link_flair_text": "Promotional",
      "permalink": "https://reddit.com/r/opensource/comments/1sbaq1u/eurooffice_european_industry_initiative_launches/",
      "domain": "nextcloud.com",
      "is_self": false,
      "comments": [
        {
          "id": "oe1wpdz",
          "author": "outerzenith",
          "text": "I'm curious on the compatibility with excel at the very least, formulas like `LET`, `XLOOKUP`, `UNIQUE`, `VSTACK` are things I can't work without anymore lol",
          "score": 7,
          "created_utc": "2026-04-03 11:21:21",
          "is_submitter": false,
          "replies": [
            {
              "id": "oe2j86a",
              "author": "APNX-23",
              "text": "It's OnlyOffice. Just check their site. I know it works with all of the basic formulas I use at work.",
              "score": 9,
              "created_utc": "2026-04-03 13:38:08",
              "is_submitter": false,
              "replies": []
            }
          ]
        },
        {
          "id": "oe61695",
          "author": "chandaliergalaxy",
          "text": "Worth noting that it is a fork of OnlyOffice, which claims this violates their open source LICENSE.\n\nhttps://itsfoss.com/news/onlyoffice-forked/",
          "score": 2,
          "created_utc": "2026-04-03 23:51:20",
          "is_submitter": false,
          "replies": [
            {
              "id": "oe6541i",
              "author": "TemporarySun314",
              "text": "Because this Russian company interprets the AGPL in a way that it would makes it impossible to do forks (as they require that every form must use their brand logo, but they don't allow anyone to use that logo)...\n\nThat goes however completely against the spirit of the AGPL and I doubt that onlyoffice's interpretation would hold in a court...",
              "score": 5,
              "created_utc": "2026-04-04 00:14:48",
              "is_submitter": false,
              "replies": [
                {
                  "id": "oe65g2k",
                  "author": "chandaliergalaxy",
                  "text": "I see. \n\nOn the other hand it's European, but also capitalist European which is not all rainbows and unicorns.",
                  "score": 2,
                  "created_utc": "2026-04-04 00:16:47",
                  "is_submitter": false,
                  "replies": []
                }
              ]
            }
          ]
        },
        {
          "id": "oe3nfsc",
          "author": "BP041",
          "text": "The Excel compatibility question is exactly the right one, and historically it's where most office suite alternatives quietly give up. The challenge isn't basic formula parity — LibreOffice handles that reasonably well — it's the combination of complex conditional formatting, VBA macro compatibility, and behaviour of newer dynamic array functions like XLOOKUP, UNIQUE, VSTACK, and LAMBDA.\n\nThe GDPR and data sovereignty angle is a genuine differentiator that previous alternatives didn't have a strong claim to. Government procurement and regulated industries where hosting on EU soil matters more than the last 2% of Excel compatibility could be the actual wedge.\n\nEnterprise adoption has historically not been a features problem. The switching cost is workflow muscle memory, IT standardisation policies, and retraining cost. The initiatives that got traction (OnlyOffice, Collabora) did so as on-premise document servers — avoiding the full desktop replacement ask.",
          "score": 0,
          "created_utc": "2026-04-03 16:47:25",
          "is_submitter": false,
          "replies": [
            {
              "id": "oe6fm4z",
              "author": "HAL_9000_DEMO",
              "text": "Clearly a bot reply.",
              "score": 6,
              "created_utc": "2026-04-04 01:18:06",
              "is_submitter": false,
              "replies": []
            }
          ]
        }
      ]
    },
    {
      "id": "1sf4s1o",
      "title": "Open Source Appreciation Day",
      "subreddit": "opensource",
      "url": "https://www.reddit.com/r/opensource/comments/1sf4s1o/open_source_appreciation_day/",
      "author": "recursive_knight",
      "created_utc": "2026-04-07 18:41:19",
      "score": 35,
      "num_comments": 3,
      "upvote_ratio": 0.93,
      "text": "Last Minute reminder: a while ago some people talked about declaring a day to celebrate open source software and donate a little something to a favourite software project. This day (07.04.) is fitting, as it marks the release of Git by Linus Torvalds. Go and support your favourite open source project! Let's start a good habit!\n\np.s. I appreciate  WifiManager by tzapu this year and couldn't find a way to donate 🫠",
      "is_original_content": false,
      "link_flair_text": "Community",
      "permalink": "https://reddit.com/r/opensource/comments/1sf4s1o/open_source_appreciation_day/",
      "domain": "self.opensource",
      "is_self": true,
      "comments": []
    },
    {
      "id": "1sd9ws6",
      "title": "Hacki - a FOSS Hacker News client",
      "subreddit": "opensource",
      "url": "https://github.com/Livinglist/Hacki",
      "author": "Adorable-Salary-5204",
      "created_utc": "2026-04-05 17:42:10",
      "score": 30,
      "num_comments": 8,
      "upvote_ratio": 0.88,
      "text": "[External Link]",
      "is_original_content": false,
      "link_flair_text": "Promotional",
      "permalink": "https://reddit.com/r/opensource/comments/1sd9ws6/hacki_a_foss_hacker_news_client/",
      "domain": "github.com",
      "is_self": false,
      "comments": [
        {
          "id": "oehrig6",
          "author": "totallyuneekname",
          "text": "That is the most screenshots I've ever seen in a README 😂",
          "score": 6,
          "created_utc": "2026-04-05 20:10:20",
          "is_submitter": false,
          "replies": [
            {
              "id": "oeip8m7",
              "author": "parkerlreed",
              "text": "It's ALL screenshots.\n\nThey must have gotten tired of people complaining there are none.",
              "score": 3,
              "created_utc": "2026-04-05 23:09:16",
              "is_submitter": false,
              "replies": []
            }
          ]
        },
        {
          "id": "oekp8z6",
          "author": "compacompila",
          "text": "This is great!!! I just installed it",
          "score": 2,
          "created_utc": "2026-04-06 07:34:22",
          "is_submitter": false,
          "replies": []
        },
        {
          "id": "oes2k8g",
          "author": "dumpshoot",
          "text": "Checked the repo and the BLoC/Cubit setup is clean, way better than most Flutter side projects I've seen where everything lives in setState calls. The ancestor lookup is the feature that would actually get me to switch from mobile web since losing context in deep HN threads is painful. Good to see it on  F-Droid too, that's usually the first thing I check.",
          "score": 2,
          "created_utc": "2026-04-07 10:55:02",
          "is_submitter": false,
          "replies": []
        },
        {
          "id": "oemnike",
          "author": "_janc_",
          "text": "You can subscribe to Hacker News using rss reader like Zephyr: rss reader",
          "score": 1,
          "created_utc": "2026-04-06 15:25:52",
          "is_submitter": false,
          "replies": []
        }
      ]
    },
    {
      "id": "1sdfpsu",
      "title": "I built a zero-dependency browser IDE as a cognitive prosthetic for my AuDHD brain. No npm. No build step. Works offline. Open source.",
      "subreddit": "opensource",
      "url": "https://www.reddit.com/r/opensource/comments/1sdfpsu/i_built_a_zerodependency_browser_ide_as_a/",
      "author": "the_rewind_guy",
      "created_utc": "2026-04-05 21:31:10",
      "score": 29,
      "num_comments": 12,
      "upvote_ratio": 0.7,
      "text": "**The problem:** I have AuDHD (Autism + ADHD) and executive dysfunction. Node.js toolchains - \\`npm install\\`, broken lockfiles, PATH issues - are a cognitive load wall I hit before I can write a single line of code. I needed an IDE that was just there.  \n\n\n**What I built:** EDE (Everything Development Environment) - a browser-native IDE that runs entirely in a service worker. No npm. No terminal. No installation. Open the URL, write code, it runs.  \n\n\nFeatures:\n\n\\- JSX transpilation in-browser (Babel standalone)\n\n\\- Offline-first via service worker\n\n\\- Spoon tracking (Q Distribution - chronic illness energy model)\n\n\\- Samson's Law entropy linter (flags cognitive overload patterns in code structure)\n\n\\- Atkinson Hyperlegible + JetBrains Mono - accessibility-first typography  \n\n\n**Try it:** [https://p31ca.org/ede](https://p31ca.org/ede)  \n\n\n**Source:** [https://github.com/p31labs/andromeda](https://github.com/p31labs/andromeda) (monorepo - EDE is in \\`04\\_SOFTWARE/p31ca/public/ede.html\\`)  \n\n\n\\---  \n\n\nEDE is one of 12 deployed products from P31 Labs - a Georgia nonprofit I incorporated April 3, 2026 to build open-source assistive tech for neurodivergent individuals. Everything runs on Cloudflare's free tier. $0 to users. No accounts required for core function.  \n\n\nThree Zenodo publications (DOIs: 10.5281/zenodo.18627420, 10.5281/zenodo.19411363, 10.5281/zenodo.19416491)  \n\n\n670+ automated tests total. Solo founder. Built while fighting to stay housed.  \n\n\nHappy to answer questions about the browser-native approach, the service worker architecture, or the accessibility design decisions.",
      "is_original_content": false,
      "link_flair_text": "Promotional",
      "permalink": "https://reddit.com/r/opensource/comments/1sdfpsu/i_built_a_zerodependency_browser_ide_as_a/",
      "domain": "self.opensource",
      "is_self": true,
      "comments": [
        {
          "id": "oel5vby",
          "author": "Speculooss",
          "text": "Fuck this. Entirely written with Claude. Not a single drop of human soul in the 150k lines of AI slop here it is truly frightening. This is a disservice to the spirit of open source.",
          "score": 43,
          "created_utc": "2026-04-06 10:07:56",
          "is_submitter": false,
          "replies": [
            {
              "id": "oelfqsk",
              "author": "edouardconstant",
              "text": "I give you the oneliner:\n\n  npm ci\n\nJoke aside, if that solves their issue it is good for them . Having it opensource might hel others and get improved",
              "score": 4,
              "created_utc": "2026-04-06 11:25:49",
              "is_submitter": false,
              "replies": []
            }
          ]
        },
        {
          "id": "oekheka",
          "author": "yaycupcake",
          "text": "Hey, this is a really cool thing and I'd love to give it a shot as this kind of tool would absolutely help me a ton in just being able to Start Doing Something since I have the same issues as you. Unfortunately I can't read or code with dark themes... Like I literally cannot visually read light text on dark background due to astigmatism. Maybe I missed it but is there a light theme option? If not, I think that's super important to add, if you care about accessibility. And if I missed where a toggle is, making it more prominent, or defaulting to the user's preferred color scheme would be amazing.",
          "score": 6,
          "created_utc": "2026-04-06 06:22:54",
          "is_submitter": false,
          "replies": []
        },
        {
          "id": "oeketno",
          "author": "hxxx07",
          "text": "nice\n\n",
          "score": 1,
          "created_utc": "2026-04-06 05:59:44",
          "is_submitter": false,
          "replies": []
        },
        {
          "id": "oekkn3a",
          "author": "revengeOfTheSquirrel",
          "text": "Amazing stuff, I love what you’re doing! As a fellow neurodivergent, may I ask how you organize yourself to not loose track of so many projects? 😂",
          "score": -1,
          "created_utc": "2026-04-06 06:52:22",
          "is_submitter": false,
          "replies": []
        }
      ]
    },
    {
      "id": "1sdsqyw",
      "title": "PeaZip 11.0.0 is ready!",
      "subreddit": "opensource",
      "url": "/r/PeaZip/comments/1sdsiwm/peazip_1100_is_ready/",
      "author": "peazip",
      "created_utc": "2026-04-06 08:10:29",
      "score": 24,
      "num_comments": 3,
      "upvote_ratio": 0.84,
      "text": "[External Link]",
      "is_original_content": false,
      "link_flair_text": null,
      "permalink": "https://reddit.com/r/opensource/comments/1sdsqyw/peazip_1100_is_ready/",
      "domain": "",
      "is_self": false,
      "comments": [
        {
          "id": "oelekm7",
          "author": "tautheory",
          "text": "another fantastic release! thanks PeaZip team!",
          "score": 4,
          "created_utc": "2026-04-06 11:17:13",
          "is_submitter": false,
          "replies": []
        }
      ]
    },
    {
      "id": "1scbuuq",
      "title": "What is happening to our Office Suites?! - Linux Weekly News",
      "subreddit": "opensource",
      "url": "https://youtu.be/eweMlWewcVg",
      "author": "AnonomousWolf",
      "created_utc": "2026-04-04 15:16:49",
      "score": 16,
      "num_comments": 0,
      "upvote_ratio": 0.83,
      "text": "[External Link]",
      "is_original_content": false,
      "link_flair_text": "Discussion",
      "permalink": "https://reddit.com/r/opensource/comments/1scbuuq/what_is_happening_to_our_office_suites_linux/",
      "domain": "youtu.be",
      "is_self": false,
      "comments": []
    },
    {
      "id": "1scr94t",
      "title": "Open Source Tools That Can Read and Map Historical Property Sale Documents?",
      "subreddit": "opensource",
      "url": "https://www.reddit.com/r/opensource/comments/1scr94t/open_source_tools_that_can_read_and_map/",
      "author": "nedraeb",
      "created_utc": "2026-04-05 01:59:22",
      "score": 10,
      "num_comments": 7,
      "upvote_ratio": 1.0,
      "text": "I have been doing some family history research. I found that old cemetery that once belonged to my family but I am pretty sure its had a house built on top of it. Anyways that is my inspiration. I still wanna find out more though one thing that would be helpful is understanding who owned what land when.\n\n  \nBasically I am thinking of a tools that can read old either tax documents or sale documents with legal descriptions and map that to a current map. There are some resources that map original land grants but I am wondering if there are any tools that map basically the entirety of land sales documents from a legal description.",
      "is_original_content": false,
      "link_flair_text": "Discussion",
      "permalink": "https://reddit.com/r/opensource/comments/1scr94t/open_source_tools_that_can_read_and_map/",
      "domain": "self.opensource",
      "is_self": true,
      "comments": [
        {
          "id": "oeddpg9",
          "author": "rka1284",
          "text": "i dont think theres one magic tool for this because old deeds are a mess, especially if they use metes and bounds instead of parcel ids. the open source stack id look at is OCRmyPDF or tesseract to get text out, then QGIS for the mapping side. qgis has a georeferencer plugin so you can line old plats or tax maps up with current parcels\n\nif the docs are mostly legal descriptions youll probably still need some manual cleanup before it maps cleanly. the annoying part isnt the OCR, its that old descriptions are often vague as hell or refer to landmarks that dont exist anymore. still definately doable though, just not one click",
          "score": 5,
          "created_utc": "2026-04-05 03:16:09",
          "is_submitter": false,
          "replies": [
            {
              "id": "oefbfp9",
              "author": "nedraeb",
              "text": "Thanks!",
              "score": 2,
              "created_utc": "2026-04-05 12:48:40",
              "is_submitter": true,
              "replies": []
            }
          ]
        },
        {
          "id": "oehzy7c",
          "author": "thinking_byte",
          "text": "We looked into something similar and the hard part isn’t OCR, it’s parsing legal land descriptions into coordinates, most open source stacks need custom pipelines with GIS tools like QGIS plus a lot of manual cleanup.",
          "score": 2,
          "created_utc": "2026-04-05 20:52:42",
          "is_submitter": false,
          "replies": []
        },
        {
          "id": "oeoi6wd",
          "author": "barrelvoyage410",
          "text": "As a land surveyor, I deeply wish this existed, but I don’t think it does.  AI struggles to read anything correctly that isn’t a perfect scan in my experience. \n\nI would not trust ai in its current form to give me accurate results. ",
          "score": 1,
          "created_utc": "2026-04-06 20:43:08",
          "is_submitter": false,
          "replies": []
        }
      ]
    },
    {
      "id": "1sasqrb",
      "title": "whats the best(cheapest) option for a phone that will actually belong to me and have good privacy",
      "subreddit": "opensource",
      "url": "https://www.reddit.com/r/opensource/comments/1sasqrb/whats_the_bestcheapest_option_for_a_phone_that/",
      "author": "[deleted]",
      "created_utc": "2026-04-02 20:27:53",
      "score": 9,
      "num_comments": 15,
      "upvote_ratio": 0.85,
      "text": "broke highschool student who broke there phone and is working a job to buy a new one",
      "is_original_content": false,
      "link_flair_text": "Alternatives",
      "permalink": "https://reddit.com/r/opensource/comments/1sasqrb/whats_the_bestcheapest_option_for_a_phone_that/",
      "domain": "self.opensource",
      "is_self": true,
      "comments": [
        {
          "id": "odz2nyz",
          "author": "thinking_byte",
          "text": "Consider buying a used or refurbished phone from a trusted platform, like eBay or Swappa, and then installing a privacy-focused OS like /e/ or GrapheneOS for better security and control over your data.",
          "score": 13,
          "created_utc": "2026-04-02 23:09:28",
          "is_submitter": false,
          "replies": []
        },
        {
          "id": "odz4ozc",
          "author": "gta721",
          "text": "A refurbished Pixel 8a or later. You can install GrapheneOS on it which is I think the most private and user freedom respecting Android OS available.",
          "score": 10,
          "created_utc": "2026-04-02 23:20:33",
          "is_submitter": false,
          "replies": []
        },
        {
          "id": "odz7m69",
          "author": "Sensitive_Box_",
          "text": "A used Pixel with GrapheneOS installed. You can get a Pixel 8 for like $200. Less if you go with an even older model.\n\n\nEdit: Oh, someone beat me to it. Lol ",
          "score": 9,
          "created_utc": "2026-04-02 23:36:50",
          "is_submitter": false,
          "replies": []
        },
        {
          "id": "odyas88",
          "author": "lothariusdark",
          "text": "The Motorola Moto G84 is a solid choice. Costs around 180$ where Im from, though I dont know where you live.\n\n[https://www.gsmarena.com/motorola\\_moto\\_g84-12526.php](https://www.gsmarena.com/motorola_moto_g84-12526.php)\n\nYou can install CalyxOS or LineageOS on it for full control.\n\nThere are honestly a bunch of Motorola budget phones that give a a lot of bang for your buck. I would suggest you look on youtube with your budget to find a fitting one. Like the \"Moto G\" model for example.",
          "score": 7,
          "created_utc": "2026-04-02 20:45:46",
          "is_submitter": false,
          "replies": []
        },
        {
          "id": "oe11js2",
          "author": "Paulchemouni",
          "text": "You might consider the Jolla phone.",
          "score": 2,
          "created_utc": "2026-04-03 06:54:49",
          "is_submitter": false,
          "replies": []
        },
        {
          "id": "oe3lw7h",
          "author": "somerandom_person1",
          "text": "Google pixel with grapheneos ",
          "score": 1,
          "created_utc": "2026-04-03 16:40:10",
          "is_submitter": false,
          "replies": []
        },
        {
          "id": "of1ppk7",
          "author": "cristiano700000",
          "text": "getting a used Pixel with GrapheneOS is probly your best bet for privacy. For cheap communication, I actully use Drop Cowboy to handle virtual numbers.  \n  \nIt works great with a Twilio ringless voicemail setup if you need to manage job calls without a huge monthly bill. Its much cheeper than a carrier",
          "score": 1,
          "created_utc": "2026-04-08 18:53:32",
          "is_submitter": false,
          "replies": []
        },
        {
          "id": "odzz80p",
          "author": "Remarkable-Emu-5718",
          "text": "A used iphone from swappa.com for around $250",
          "score": -2,
          "created_utc": "2026-04-03 02:17:49",
          "is_submitter": false,
          "replies": []
        },
        {
          "id": "ody9ctz",
          "author": "Trying_to_cod3",
          "text": "the cheapest option I can think of would be to get a raspberry pi phone, [(pi-phone)](https://www.raspberrypi.com/news/piphone-home-made-raspberry-pi-smartphone/). Costs 158$ and you can do calls and texts, but it will be a bit annoying to set up",
          "score": -6,
          "created_utc": "2026-04-02 20:38:55",
          "is_submitter": false,
          "replies": []
        }
      ]
    },
    {
      "id": "1sepfhw",
      "title": "Open source macOS secret manager for developers",
      "subreddit": "opensource",
      "url": "https://github.com/ilmakio/PassStore",
      "author": "ilMakio",
      "created_utc": "2026-04-07 07:46:34",
      "score": 8,
      "num_comments": 10,
      "upvote_ratio": 0.78,
      "text": "[External Link]",
      "is_original_content": false,
      "link_flair_text": "Promotional",
      "permalink": "https://reddit.com/r/opensource/comments/1sepfhw/open_source_macos_secret_manager_for_developers/",
      "domain": "github.com",
      "is_self": false,
      "comments": [
        {
          "id": "oezr8o0",
          "author": "HEATH_CLIFF__",
          "text": "I'll try this out ",
          "score": 1,
          "created_utc": "2026-04-08 13:33:57",
          "is_submitter": false,
          "replies": [
            {
              "id": "oezscj5",
              "author": "ilMakio",
              "text": "Thank you! Let me know if you have some feedback ",
              "score": 1,
              "created_utc": "2026-04-08 13:39:32",
              "is_submitter": true,
              "replies": []
            }
          ]
        },
        {
          "id": "of3tpsa",
          "author": "Distinct_Group_3813",
          "text": "Does it support migrating to another mac?",
          "score": 1,
          "created_utc": "2026-04-09 01:17:11",
          "is_submitter": false,
          "replies": [
            {
              "id": "of58n85",
              "author": "ilMakio",
              "text": "Migration is possible, but not through cloud or sync. You can export an encrypted backup and reimport it on another Mac using the password you selected!",
              "score": 1,
              "created_utc": "2026-04-09 07:14:43",
              "is_submitter": true,
              "replies": []
            }
          ]
        },
        {
          "id": "of53xta",
          "author": "ay3524",
          "text": "will give this a try!",
          "score": 1,
          "created_utc": "2026-04-09 06:34:07",
          "is_submitter": false,
          "replies": [
            {
              "id": "of58nyq",
              "author": "ilMakio",
              "text": "Let me know!",
              "score": 1,
              "created_utc": "2026-04-09 07:14:54",
              "is_submitter": true,
              "replies": []
            }
          ]
        }
      ]
    },
    {
      "id": "1sc65ij",
      "title": "I forked IT-Tools and turned it into an MSP/sysadmin-focused toolkit",
      "subreddit": "opensource",
      "url": "https://www.reddit.com/r/opensource/comments/1sc65ij/i_forked_ittools_and_turned_it_into_an/",
      "author": "smilaise",
      "created_utc": "2026-04-04 10:50:48",
      "score": 7,
      "num_comments": 2,
      "upvote_ratio": 0.77,
      "text": "I've been building on top of IT-Tools (the Vue/Vite utility toolkit) for a while now, adding a bunch of tools specific to my work in IT. Things like WHOIS via RDAP, email header parsing, a big port reference, Windows event ID and GPO lookups, M365 SKU decoder, powershell builder...\n\n\n\n[killertools.net](http://killertools.net)\n\n\n\nIt's a static site hosted on GitHub Pages. Everything runs client-side, no backend, no accounts, no ads. The repo is public on GitHub.\n\n\n\nI'm still actively adding tools. If anyone wants to poke around or contribute, the repo is there. Feedback welcome.\n\n\n\n[https://github.com/SteveTheKiller/killer-tools-site](https://github.com/SteveTheKiller/killer-tools-site)",
      "is_original_content": false,
      "link_flair_text": "Promotional",
      "permalink": "https://reddit.com/r/opensource/comments/1sc65ij/i_forked_ittools_and_turned_it_into_an/",
      "domain": "self.opensource",
      "is_self": true,
      "comments": []
    },
    {
      "id": "1scigbz",
      "title": "driveTree — open-source Google Drive folder browser (GPL v3)",
      "subreddit": "opensource",
      "url": "https://www.reddit.com/r/opensource/comments/1scigbz/drivetree_opensource_google_drive_folder_browser/",
      "author": "sMASS_",
      "created_utc": "2026-04-04 19:34:56",
      "score": 7,
      "num_comments": 6,
      "upvote_ratio": 1.0,
      "text": "I just released driveTree, a free tool that gives any public Google Drive folder a clean, GitHub-style file browsing experience. Syntax highlighting, file tree, downloads, shareable links.\n\n[drivetree.net](https://drivetree.net) | [Source on GitHub](https://github.com/SeidSmatti/drivetree)\n\nBuilt with SvelteKit, runs on Cloudflare's free tier. Licensed under GPL v3. No tracking, no accounts, no data collection.\n\nI built it because Google Drive's native UI is terrible for sharing code, project files, or course materials. Happy to hear feedback or accept contributions!\n\n",
      "is_original_content": false,
      "link_flair_text": "Promotional",
      "permalink": "https://reddit.com/r/opensource/comments/1scigbz/drivetree_opensource_google_drive_folder_browser/",
      "domain": "self.opensource",
      "is_self": true,
      "comments": []
    },
    {
      "id": "1sdsimd",
      "title": "termtrace: replay terminal workflows step by step.",
      "subreddit": "opensource",
      "url": "https://github.com/AmalChandru/termtrace",
      "author": "Ok-Huckleberry5617",
      "created_utc": "2026-04-06 07:56:11",
      "score": 6,
      "num_comments": 2,
      "upvote_ratio": 0.88,
      "text": "[External Link]",
      "is_original_content": false,
      "link_flair_text": "Promotional",
      "permalink": "https://reddit.com/r/opensource/comments/1sdsimd/termtrace_replay_terminal_workflows_step_by_step/",
      "domain": "github.com",
      "is_self": false,
      "comments": [
        {
          "id": "oekrq4w",
          "author": "Ok-Huckleberry5617",
          "text": "Replay demo -> https://github.com/AmalChandru/termtrace/blob/main/assets/replay.mp4",
          "score": 1,
          "created_utc": "2026-04-06 07:57:09",
          "is_submitter": true,
          "replies": []
        }
      ]
    },
    {
      "id": "1scitry",
      "title": "What OS must I use if i want more control on my Xiaomi phone( I want to be able to run custom code on it... basically something like linux) But still have access to camera, mobile data and phone graphics acceleration. And also reduce bloatware.",
      "subreddit": "opensource",
      "url": "https://www.reddit.com/r/opensource/comments/1scitry/what_os_must_i_use_if_i_want_more_control_on_my/",
      "author": "Fancy-Caregiver-1239",
      "created_utc": "2026-04-04 19:49:45",
      "score": 6,
      "num_comments": 10,
      "upvote_ratio": 0.75,
      "text": "",
      "is_original_content": false,
      "link_flair_text": "Discussion",
      "permalink": "https://reddit.com/r/opensource/comments/1scitry/what_os_must_i_use_if_i_want_more_control_on_my/",
      "domain": "self.opensource",
      "is_self": true,
      "comments": [
        {
          "id": "oebgbl6",
          "author": "Jimm144",
          "text": "To run code get termux and to reduce bloatware get shizuku, activate it and download canta (these are all apps and on f droid)",
          "score": 7,
          "created_utc": "2026-04-04 20:35:08",
          "is_submitter": false,
          "replies": [
            {
              "id": "oebh1qo",
              "author": "Fancy-Caregiver-1239",
              "text": "Hey. Thank you for the response.. I was initially thinking about lineageos. How is that option.\nAlso I want the script to run every time the phone starts... Doesn't matter even if other apps and UI don't show up. But I want access to all the things I mentioned (camera, etc.)",
              "score": 2,
              "created_utc": "2026-04-04 20:38:47",
              "is_submitter": true,
              "replies": []
            }
          ]
        },
        {
          "id": "oebhclh",
          "author": "Devatator_",
          "text": "Honestly any supported 3rd party ROM should be fine. I'm personally using Matrixx but that's because it was the stablest of the few I could find for my Redmi Note 11 (also no weird incompatibilities, like EvolutionX breaking hardware video decoders, making YouTube and other video players unwatchable)\n\nEdit: Also root if you want total control",
          "score": 3,
          "created_utc": "2026-04-04 20:40:19",
          "is_submitter": false,
          "replies": []
        },
        {
          "id": "oeewumq",
          "author": "kadir1243",
          "text": "Idk your phone so i cant tell is it supported but maybe you are looking for postmarketos",
          "score": 2,
          "created_utc": "2026-04-05 11:03:27",
          "is_submitter": false,
          "replies": []
        },
        {
          "id": "of0szo9",
          "author": "borakostem",
          "text": "LineageOS",
          "score": 2,
          "created_utc": "2026-04-08 16:27:19",
          "is_submitter": false,
          "replies": []
        }
      ]
    },
    {
      "id": "1sf8jvy",
      "title": "Lightweight subtractive scheduling tool designed to minimize the time you spend using it",
      "subreddit": "opensource",
      "url": "https://www.reddit.com/r/opensource/comments/1sf8jvy/lightweight_subtractive_scheduling_tool_designed/",
      "author": "squakmix",
      "created_utc": "2026-04-07 20:59:58",
      "score": 6,
      "num_comments": 4,
      "upvote_ratio": 1.0,
      "text": "I missed the old lightweight scheduling tools from 10 to 15 years ago that allowed me to quickly create a poll and send out a URL without any logins required (like the old Doodle polls). I couldn't find a FOSS alternative that used a subtractive model so users could get in, select schedule conflicts, and leave the site immediately.\n\nSo I built a free edge service version on cloudflare D1 with vanilla JS, so it's guaranteed to never be enshittified.\n\nThis was a little weekend project that I built for myself and my groups, but figured some folks here might get some use out of it. I'm interested in hearing about any issues or ideas for improvement.\n\nIt's live now at: https://timeslot.ink https://github.com/solderlocks/timeslot",
      "is_original_content": false,
      "link_flair_text": "Promotional",
      "permalink": "https://reddit.com/r/opensource/comments/1sf8jvy/lightweight_subtractive_scheduling_tool_designed/",
      "domain": "self.opensource",
      "is_self": true,
      "comments": []
    },
    {
      "id": "1sf6i86",
      "title": "Really good open source project to join as an unemployed developer looking for practice with microservices and full stack?",
      "subreddit": "opensource",
      "url": "https://www.reddit.com/r/opensource/comments/1sf6i86/really_good_open_source_project_to_join_as_an/",
      "author": "Impossible_Gift8457",
      "created_utc": "2026-04-07 19:43:27",
      "score": 5,
      "num_comments": 11,
      "upvote_ratio": 0.67,
      "text": "",
      "is_original_content": false,
      "link_flair_text": "Community",
      "permalink": "https://reddit.com/r/opensource/comments/1sf6i86/really_good_open_source_project_to_join_as_an/",
      "domain": "self.opensource",
      "is_self": true,
      "comments": [
        {
          "id": "oewqhm2",
          "author": "_redacted-",
          "text": "I could use some help. UnicornCommander.com ",
          "score": 2,
          "created_utc": "2026-04-08 00:47:11",
          "is_submitter": false,
          "replies": [
            {
              "id": "of0aniy",
              "author": "Impossible_Gift8457",
              "text": "Do you have a discord group?",
              "score": 1,
              "created_utc": "2026-04-08 15:05:20",
              "is_submitter": true,
              "replies": []
            }
          ]
        },
        {
          "id": "of19uw6",
          "author": "cataklix",
          "text": "Mine : https://atomic-blend.com",
          "score": 2,
          "created_utc": "2026-04-08 17:42:18",
          "is_submitter": false,
          "replies": []
        }
      ]
    }
  ]
}